smart_logging
