Metadata-Version: 2.1
Name: django-smart-logging
Version: 0.4.0
Summary: UNKNOWN
Home-page: https://gitlab.com/os4d/django-smart-logging.git
Author: sax
Author-email: s.apostolico@gmail.com
License: MIT
Download-URL: https://gitlab.com/os4d/django-smart-logging
Platform: any
Classifier: Environment :: Web Environment
Classifier: Framework :: Django
Classifier: Operating System :: OS Independent
Classifier: Framework :: Django :: 3.2
Classifier: Framework :: Django :: 4.0
Classifier: Programming Language :: Python :: 3.9
Classifier: Programming Language :: Python :: 3.10
Classifier: Intended Audience :: Developers
Provides-Extra: test
Provides-Extra: dev
Provides-Extra: docs
License-File: LICENSE
